<?xml version="1.0" encoding="UTF-8" standalone="no" ?><CAERep ObjId="231" Type="CAERep" Ver="2"><DSEnvironmentID PropType="int">47</DSEnvironmentID><ExternalProductVersion PropType="string">2023 R1</ExternalProductVersion><Goal PropType="string">RunSolver</Goal><HasBetaKeyOn PropType="bool">false</HasBetaKeyOn><InProcess PropType="bool">true</InProcess><LastDatabaseId PropType="unsigned int">284</LastDatabaseId><NumProcessorsForPost PropType="int">0</NumProcessorsForPost><PID_Legacy_Solve PropType="int">0</PID_Legacy_Solve><PartialCode PropType="int">1</PartialCode><ProductVersion PropType="string">23.1 RELEASE</ProductVersion><ProductVersionForSec PropType="string">23.1</ProductVersionForSec><ProjectName PropType="string">test--Modal (K5)</ProjectName><ReturnCode PropType="int">1</ReturnCode><SolveInvokedFromAddin PropType="int">0</SolveInvokedFromAddin><SysvarMap PropType="map&lt;string,string>"><Entry key="DSSolver ProgId">AMKSolver.AMKSolver.231</Entry></SysvarMap><EngineeringRep ObjId="232" Type="EngineeringRep" Ver="2"><BCRep ObjId="235" Type="BCRep" Ver="2"><StepEndTimes PropType="vector&lt;double>" UCat="Time" Unt="s">    1</StepEndTimes><ContactRep ObjId="164" Type="ContactRep" Ver="3"><Behavior PropType="string">ProgramControlled</Behavior><Breakable PropType="string">No</Breakable><Caption PropType="string">Contact Region</Caption><CondensedPartId PropType="int">0</CondensedPartId><DecayConstant PropType="double">    0</DecayConstant><DetectionMethod PropType="string">ProgramControlled</DetectionMethod><DynamicCoefficient PropType="double">    0</DynamicCoefficient><Formulation PropType="string">ProgramControlledContact</Formulation><IsNative PropType="bool">true</IsNative><IsPromoted PropType="bool">false</IsPromoted><MaximumOffset PropType="double" UCat="Length" Unt="m">1e-07</MaximumOffset><Restitution PropType="double">    1</Restitution><Scoping PropType="vector&lt;string>">165,166</Scoping><ScopingSubset0 PropType="vector&lt;string>">165</ScopingSubset0><ScopingSubset1 PropType="vector&lt;string>">166</ScopingSubset1><ShellThicknessEffect PropType="string">No</ShellThicknessEffect><SmallSliding PropType="string">ProgramControlled</SmallSliding><SourceBodyIds PropType="vector&lt;unsigned int>">161</SourceBodyIds><StaticCoefficient PropType="double">    0</StaticCoefficient><TargetBodyIds PropType="vector&lt;unsigned int>">171</TargetBodyIds><TrimTolerance PropType="double" UCat="Length" Unt="m">5.295280940820646e-05</TrimTolerance><TrimType PropType="string">ProgramControlled</TrimType><Type PropType="string">Bonded</Type><UseAutoElasticSlipTolerance PropType="string">ProgramControlled</UseAutoElasticSlipTolerance><UseAutoPenetrationTolerance PropType="string">ProgramControlled</UseAutoPenetrationTolerance><SourceReference ObjId="272" Type="CAERepBase" Ver="2"><ReferenceId PropType="unsigned int">158</ReferenceId><ReferenceType PropType="vector&lt;string>">Edge,Line</ReferenceType></SourceReference><TargetReference ObjId="273" Type="CAERepBase" Ver="2"><ReferenceId PropType="unsigned int">167</ReferenceId><ReferenceType PropType="vector&lt;string>">Edge,Line</ReferenceType></TargetReference><Pinball ObjId="271" Type="Pinball" Ver="2"><Type PropType="string">ProgramControlled</Type></Pinball><ProgramControlledContact ObjId="270" Type="ProgramControlledContact" Ver="2"><UpdateStiffness PropType="string">Never</UpdateStiffness><UseAutoElectricalConductance PropType="bool">true</UseAutoElectricalConductance><UseAutoNormalStiffness PropType="bool">true</UseAutoNormalStiffness><UseAutoThermalConductance PropType="bool">true</UseAutoThermalConductance></ProgramControlledContact></ContactRep><ContactRep ObjId="167" Type="ContactRep" Ver="3"><Behavior PropType="string">ProgramControlled</Behavior><Breakable PropType="string">No</Breakable><Caption PropType="string">Contact Region 2</Caption><CondensedPartId PropType="int">0</CondensedPartId><DecayConstant PropType="double">    0</DecayConstant><DetectionMethod PropType="string">ProgramControlled</DetectionMethod><DynamicCoefficient PropType="double">    0</DynamicCoefficient><Formulation PropType="string">ProgramControlledContact</Formulation><IsNative PropType="bool">true</IsNative><IsPromoted PropType="bool">false</IsPromoted><MaximumOffset PropType="double" UCat="Length" Unt="m">1e-07</MaximumOffset><Restitution PropType="double">    1</Restitution><Scoping PropType="vector&lt;string>">168,169</Scoping><ScopingSubset0 PropType="vector&lt;string>">168</ScopingSubset0><ScopingSubset1 PropType="vector&lt;string>">169</ScopingSubset1><ShellThicknessEffect PropType="string">No</ShellThicknessEffect><SmallSliding PropType="string">ProgramControlled</SmallSliding><SourceBodyIds PropType="vector&lt;unsigned int>">161</SourceBodyIds><StaticCoefficient PropType="double">    0</StaticCoefficient><TargetBodyIds PropType="vector&lt;unsigned int>">181</TargetBodyIds><TrimTolerance PropType="double" UCat="Length" Unt="m">5.295280940820646e-05</TrimTolerance><TrimType PropType="string">ProgramControlled</TrimType><Type PropType="string">Bonded</Type><UseAutoElasticSlipTolerance PropType="string">ProgramControlled</UseAutoElasticSlipTolerance><UseAutoPenetrationTolerance PropType="string">ProgramControlled</UseAutoPenetrationTolerance><SourceReference ObjId="276" Type="CAERepBase" Ver="2"><ReferenceId PropType="unsigned int">160</ReferenceId><ReferenceType PropType="vector&lt;string>">Edge,Line</ReferenceType></SourceReference><TargetReference ObjId="277" Type="CAERepBase" Ver="2"><ReferenceId PropType="unsigned int">177</ReferenceId><ReferenceType PropType="vector&lt;string>">Edge,Line</ReferenceType></TargetReference><Pinball ObjId="275" Type="Pinball" Ver="2"><Type PropType="string">ProgramControlled</Type></Pinball><ProgramControlledContact ObjId="274" Type="ProgramControlledContact" Ver="2"><UpdateStiffness PropType="string">Never</UpdateStiffness><UseAutoElectricalConductance PropType="bool">true</UseAutoElectricalConductance><UseAutoNormalStiffness PropType="bool">true</UseAutoNormalStiffness><UseAutoThermalConductance PropType="bool">true</UseAutoThermalConductance></ProgramControlledContact></ContactRep><ContactRep ObjId="170" Type="ContactRep" Ver="3"><Behavior PropType="string">ProgramControlled</Behavior><Breakable PropType="string">No</Breakable><Caption PropType="string">Contact Region 3</Caption><CondensedPartId PropType="int">0</CondensedPartId><DecayConstant PropType="double">    0</DecayConstant><DetectionMethod PropType="string">ProgramControlled</DetectionMethod><DynamicCoefficient PropType="double">    0</DynamicCoefficient><Formulation PropType="string">ProgramControlledContact</Formulation><IsNative PropType="bool">true</IsNative><IsPromoted PropType="bool">false</IsPromoted><MaximumOffset PropType="double" UCat="Length" Unt="m">1e-07</MaximumOffset><Restitution PropType="double">    1</Restitution><Scoping PropType="vector&lt;string>">171,172</Scoping><ScopingSubset0 PropType="vector&lt;string>">171</ScopingSubset0><ScopingSubset1 PropType="vector&lt;string>">172</ScopingSubset1><ShellThicknessEffect PropType="string">No</ShellThicknessEffect><SmallSliding PropType="string">ProgramControlled</SmallSliding><SourceBodyIds PropType="vector&lt;unsigned int>">181</SourceBodyIds><StaticCoefficient PropType="double">    0</StaticCoefficient><TargetBodyIds PropType="vector&lt;unsigned int>">191</TargetBodyIds><TrimTolerance PropType="double" UCat="Length" Unt="m">5.295280940820646e-05</TrimTolerance><TrimType PropType="string">ProgramControlled</TrimType><Type PropType="string">Bonded</Type><UseAutoElasticSlipTolerance PropType="string">ProgramControlled</UseAutoElasticSlipTolerance><UseAutoPenetrationTolerance PropType="string">ProgramControlled</UseAutoPenetrationTolerance><SourceReference ObjId="280" Type="CAERepBase" Ver="2"><ReferenceId PropType="unsigned int">179</ReferenceId><ReferenceType PropType="vector&lt;string>">Edge,Line</ReferenceType></SourceReference><TargetReference ObjId="281" Type="CAERepBase" Ver="2"><ReferenceId PropType="unsigned int">187</ReferenceId><ReferenceType PropType="vector&lt;string>">Edge,Line</ReferenceType></TargetReference><Pinball ObjId="279" Type="Pinball" Ver="2"><Type PropType="string">ProgramControlled</Type></Pinball><ProgramControlledContact ObjId="278" Type="ProgramControlledContact" Ver="2"><UpdateStiffness PropType="string">Never</UpdateStiffness><UseAutoElectricalConductance PropType="bool">true</UseAutoElectricalConductance><UseAutoNormalStiffness PropType="bool">true</UseAutoNormalStiffness><UseAutoThermalConductance PropType="bool">true</UseAutoThermalConductance></ProgramControlledContact></ContactRep></BCRep><GeometryAttributes ObjId="233" Type="GeometryAttributes" Ver="2"><AssemblyAttributes ObjId="234" Type="AssemblyAttributes" Ver="2"><ElementOptionControl PropType="string">ProgramControlled</ElementOptionControl><GeometrySource PropType="string">C:\Users\simon\Desktop\Test Ansys - Copia\test_files\dp0\Geom-5\DM\Geom-5.agdb</GeometrySource><Is2DAnalysis PropType="bool">true</Is2DAnalysis><IsMixedDimension PropType="bool">false</IsMixedDimension><Model2dBehavior PropType="string">AxiSymmetric</Model2dBehavior><PartAttributes ObjId="152" Type="PartAttributes" Ver="2"><Caption PropType="string">Surface Body</Caption><Mass PropType="double" UCat="Mass" Unt="kg">    0</Mass><PartId PropType="unsigned int">150</PartId><BodyAttributes ObjId="153" Type="BodyAttributes" Ver="2"><AreNonLinearEffectsOn PropType="bool">true</AreNonLinearEffectsOn><BoundingBoxDiagonal PropType="double" UCat="Length" Unt="m">0.004123105849689533</BoundingBoxDiagonal><Caption PropType="string">Surface Body</Caption><ElementCoordSysId PropType="unsigned int">36</ElementCoordSysId><GeometryType PropType="string">Sheet</GeometryType><Mass PropType="double" UCat="Mass" Unt="kg">    0</Mass><ProtoReferenceId PropType="unsigned int">161</ProtoReferenceId><StiffnessBehavior PropType="string">Deformable</StiffnessBehavior><ThermalStrainCalculation PropType="bool">true</ThermalStrainCalculation><MassMomentOfInertia ObjId="241" Type="MassMomentOfInertia" Ver="2"><Ixx PropType="double" UCat="MomentInertiaMass" Unt="kg m^2">2.593334731753469e-12</Ixx><Iyy PropType="double" UCat="MomentInertiaMass" Unt="kg m^2">4.149334604710886e-11</Iyy><Izz PropType="double" UCat="MomentInertiaMass" Unt="kg m^2">4.408668077886293e-11</Izz></MassMomentOfInertia><MaterialRep ObjId="240" Type="MaterialRep" Ver="2"><MaterialName PropType="string">PZ 21</MaterialName><ReferenceTemperature PropType="double" UCat="Temperature" Unt="Celsius">   22</ReferenceTemperature><RelaxationTemperature PropType="double" UCat="Temperature" Unt="Celsius">    0</RelaxationTemperature><UnitSystem PropType="int">0</UnitSystem><UseReferenceTemperature PropType="bool">false</UseReferenceTemperature><UseRelaxationTemperature PropType="bool">false</UseRelaxationTemperature></MaterialRep></BodyAttributes><Centroid ObjId="242" Type="DSGePoint3d" Ver="3"><Coordinates PropType="vector&lt;double>" UCat="Length" Unt="m">0.002000000094994702,0.0109000001102675,    0</Coordinates></Centroid><MassMomentOfInertia ObjId="243" Type="MassMomentOfInertia" Ver="2"><Ixx PropType="double" UCat="MomentInertiaMass" Unt="kg m^2">2.593334731753469e-12</Ixx><Iyy PropType="double" UCat="MomentInertiaMass" Unt="kg m^2">4.149334604710886e-11</Iyy><Izz PropType="double" UCat="MomentInertiaMass" Unt="kg m^2">4.408668077886293e-11</Izz><CoordinateSystemRep ObjId="244" Type="CoordinateSystemRep" Ver="3"><Caption PropType="string">Undefined</Caption><CoordSystemIndex PropType="unsigned int">0</CoordSystemIndex><IsGlobal PropType="bool">false</IsGlobal><Param1 PropType="double">    1</Param1><Param2 PropType="double">    1</Param2><Singularity1 PropType="int">0</Singularity1><Singularity2 PropType="int">0</Singularity2><SolverCoordNumber PropType="unsigned int">0</SolverCoordNumber><Type PropType="string">Cartesian</Type><DSGePoint3d ObjId="246" Type="DSGePoint3d" Ver="3"><Coordinates PropType="vector&lt;double>" UCat="Length" Unt="m">0.002000000094994702,0.0109000001102675,    0</Coordinates></DSGePoint3d><Matrix3X3 ObjId="245" Type="Matrix3X3" Ver="2"><IsOrthogonal PropType="bool">false</IsOrthogonal><Row0 PropType="vector&lt;double>">    1,    0,    0</Row0><Row1 PropType="vector&lt;double>">    0,    1,    0</Row1><Row2 PropType="vector&lt;double>">    0,    0,    1</Row2></Matrix3X3></CoordinateSystemRep></MassMomentOfInertia></PartAttributes><PartAttributes ObjId="155" Type="PartAttributes" Ver="2"><Caption PropType="string">Surface Body</Caption><Mass PropType="double" UCat="Mass" Unt="kg">    0</Mass><PartId PropType="unsigned int">152</PartId><BodyAttributes ObjId="156" Type="BodyAttributes" Ver="2"><AreNonLinearEffectsOn PropType="bool">true</AreNonLinearEffectsOn><BoundingBoxDiagonal PropType="double" UCat="Length" Unt="m">0.01021567418091571</BoundingBoxDiagonal><Caption PropType="string">Surface Body</Caption><ElementCoordSysId PropType="unsigned int">36</ElementCoordSysId><GeometryType PropType="string">Sheet</GeometryType><Mass PropType="double" UCat="Mass" Unt="kg">    0</Mass><ProtoReferenceId PropType="unsigned int">171</ProtoReferenceId><StiffnessBehavior PropType="string">Deformable</StiffnessBehavior><ThermalStrainCalculation PropType="bool">true</ThermalStrainCalculation><MassMomentOfInertia ObjId="248" Type="MassMomentOfInertia" Ver="2"><Ixx PropType="double" UCat="MomentInertiaMass" Unt="kg m^2">1.24781403460008e-09</Ixx><Iyy PropType="double" UCat="MomentInertiaMass" Unt="kg m^2">2.259509622701615e-10</Iyy><Izz PropType="double" UCat="MomentInertiaMass" Unt="kg m^2">1.473764996870251e-09</Izz></MassMomentOfInertia><MaterialRep ObjId="247" Type="MaterialRep" Ver="2"><MaterialName PropType="string">Titanio</MaterialName><ReferenceTemperature PropType="double" UCat="Temperature" Unt="Celsius">   22</ReferenceTemperature><RelaxationTemperature PropType="double" UCat="Temperature" Unt="Celsius">    0</RelaxationTemperature><UnitSystem PropType="int">0</UnitSystem><UseReferenceTemperature PropType="bool">false</UseReferenceTemperature><UseRelaxationTemperature PropType="bool">false</UseRelaxationTemperature></MaterialRep></BodyAttributes><Centroid ObjId="249" Type="DSGePoint3d" Ver="3"><Coordinates PropType="vector&lt;double>" UCat="Length" Unt="m">0.002000000094994702,0.01610000012442308,    0</Coordinates></Centroid><MassMomentOfInertia ObjId="250" Type="MassMomentOfInertia" Ver="2"><Ixx PropType="double" UCat="MomentInertiaMass" Unt="kg m^2">1.24781403460008e-09</Ixx><Iyy PropType="double" UCat="MomentInertiaMass" Unt="kg m^2">2.259509622701615e-10</Iyy><Izz PropType="double" UCat="MomentInertiaMass" Unt="kg m^2">1.473764996870251e-09</Izz><CoordinateSystemRep ObjId="251" Type="CoordinateSystemRep" Ver="3"><Caption PropType="string">Undefined</Caption><CoordSystemIndex PropType="unsigned int">0</CoordSystemIndex><IsGlobal PropType="bool">false</IsGlobal><Param1 PropType="double">    1</Param1><Param2 PropType="double">    1</Param2><Singularity1 PropType="int">0</Singularity1><Singularity2 PropType="int">0</Singularity2><SolverCoordNumber PropType="unsigned int">0</SolverCoordNumber><Type PropType="string">Cartesian</Type><DSGePoint3d ObjId="253" Type="DSGePoint3d" Ver="3"><Coordinates PropType="vector&lt;double>" UCat="Length" Unt="m">0.002000000094994702,0.01610000012442308,    0</Coordinates></DSGePoint3d><Matrix3X3 ObjId="252" Type="Matrix3X3" Ver="2"><IsOrthogonal PropType="bool">false</IsOrthogonal><Row0 PropType="vector&lt;double>">    1,    0,    0</Row0><Row1 PropType="vector&lt;double>">    0,    1,    0</Row1><Row2 PropType="vector&lt;double>">    0,    0,    1</Row2></Matrix3X3></CoordinateSystemRep></MassMomentOfInertia></PartAttributes><PartAttributes ObjId="158" Type="PartAttributes" Ver="2"><Caption PropType="string">Surface Body</Caption><Mass PropType="double" UCat="Mass" Unt="kg">    0</Mass><PartId PropType="unsigned int">154</PartId><BodyAttributes ObjId="159" Type="BodyAttributes" Ver="2"><AreNonLinearEffectsOn PropType="bool">true</AreNonLinearEffectsOn><BoundingBoxDiagonal PropType="double" UCat="Length" Unt="m">0.004123105849689533</BoundingBoxDiagonal><Caption PropType="string">Surface Body</Caption><ElementCoordSysId PropType="unsigned int">36</ElementCoordSysId><GeometryType PropType="string">Sheet</GeometryType><Mass PropType="double" UCat="Mass" Unt="kg">    0</Mass><ProtoReferenceId PropType="unsigned int">181</ProtoReferenceId><StiffnessBehavior PropType="string">Deformable</StiffnessBehavior><ThermalStrainCalculation PropType="bool">true</ThermalStrainCalculation><MassMomentOfInertia ObjId="255" Type="MassMomentOfInertia" Ver="2"><Ixx PropType="double" UCat="MomentInertiaMass" Unt="kg m^2">2.593334731752263e-12</Ixx><Iyy PropType="double" UCat="MomentInertiaMass" Unt="kg m^2">4.149334604710884e-11</Iyy><Izz PropType="double" UCat="MomentInertiaMass" Unt="kg m^2">4.408668077886092e-11</Izz></MassMomentOfInertia><MaterialRep ObjId="254" Type="MaterialRep" Ver="2"><MaterialName PropType="string">PZ 21</MaterialName><ReferenceTemperature PropType="double" UCat="Temperature" Unt="Celsius">   22</ReferenceTemperature><RelaxationTemperature PropType="double" UCat="Temperature" Unt="Celsius">    0</RelaxationTemperature><UnitSystem PropType="int">0</UnitSystem><UseReferenceTemperature PropType="bool">false</UseReferenceTemperature><UseRelaxationTemperature PropType="bool">false</UseRelaxationTemperature></MaterialRep></BodyAttributes><Centroid ObjId="256" Type="DSGePoint3d" Ver="3"><Coordinates PropType="vector&lt;double>" UCat="Length" Unt="m">0.002000000094994702,0.009899999946354829,    0</Coordinates></Centroid><MassMomentOfInertia ObjId="257" Type="MassMomentOfInertia" Ver="2"><Ixx PropType="double" UCat="MomentInertiaMass" Unt="kg m^2">2.593334731752263e-12</Ixx><Iyy PropType="double" UCat="MomentInertiaMass" Unt="kg m^2">4.149334604710884e-11</Iyy><Izz PropType="double" UCat="MomentInertiaMass" Unt="kg m^2">4.408668077886092e-11</Izz><CoordinateSystemRep ObjId="258" Type="CoordinateSystemRep" Ver="3"><Caption PropType="string">Undefined</Caption><CoordSystemIndex PropType="unsigned int">0</CoordSystemIndex><IsGlobal PropType="bool">false</IsGlobal><Param1 PropType="double">    1</Param1><Param2 PropType="double">    1</Param2><Singularity1 PropType="int">0</Singularity1><Singularity2 PropType="int">0</Singularity2><SolverCoordNumber PropType="unsigned int">0</SolverCoordNumber><Type PropType="string">Cartesian</Type><DSGePoint3d ObjId="260" Type="DSGePoint3d" Ver="3"><Coordinates PropType="vector&lt;double>" UCat="Length" Unt="m">0.002000000094994702,0.009899999946354829,    0</Coordinates></DSGePoint3d><Matrix3X3 ObjId="259" Type="Matrix3X3" Ver="2"><IsOrthogonal PropType="bool">false</IsOrthogonal><Row0 PropType="vector&lt;double>">    1,    0,    0</Row0><Row1 PropType="vector&lt;double>">    0,    1,    0</Row1><Row2 PropType="vector&lt;double>">    0,    0,    1</Row2></Matrix3X3></CoordinateSystemRep></MassMomentOfInertia></PartAttributes><PartAttributes ObjId="161" Type="PartAttributes" Ver="2"><Caption PropType="string">Surface Body</Caption><Mass PropType="double" UCat="Mass" Unt="kg">    0</Mass><PartId PropType="unsigned int">156</PartId><BodyAttributes ObjId="162" Type="BodyAttributes" Ver="2"><AreNonLinearEffectsOn PropType="bool">true</AreNonLinearEffectsOn><BoundingBoxDiagonal PropType="double" UCat="Length" Unt="m">0.01021567418091571</BoundingBoxDiagonal><Caption PropType="string">Surface Body</Caption><ElementCoordSysId PropType="unsigned int">36</ElementCoordSysId><GeometryType PropType="string">Sheet</GeometryType><Mass PropType="double" UCat="Mass" Unt="kg">    0</Mass><ProtoReferenceId PropType="unsigned int">191</ProtoReferenceId><StiffnessBehavior PropType="string">Deformable</StiffnessBehavior><ThermalStrainCalculation PropType="bool">true</ThermalStrainCalculation><MassMomentOfInertia ObjId="262" Type="MassMomentOfInertia" Ver="2"><Ixx PropType="double" UCat="MomentInertiaMass" Unt="kg m^2">1.247814034600073e-09</Ixx><Iyy PropType="double" UCat="MomentInertiaMass" Unt="kg m^2">2.259509622701612e-10</Iyy><Izz PropType="double" UCat="MomentInertiaMass" Unt="kg m^2">1.473764996870234e-09</Izz></MassMomentOfInertia><MaterialRep ObjId="261" Type="MaterialRep" Ver="2"><MaterialName PropType="string">Titanio</MaterialName><ReferenceTemperature PropType="double" UCat="Temperature" Unt="Celsius">   22</ReferenceTemperature><RelaxationTemperature PropType="double" UCat="Temperature" Unt="Celsius">    0</RelaxationTemperature><UnitSystem PropType="int">0</UnitSystem><UseReferenceTemperature PropType="bool">false</UseReferenceTemperature><UseRelaxationTemperature PropType="bool">false</UseRelaxationTemperature></MaterialRep></BodyAttributes><Centroid ObjId="263" Type="DSGePoint3d" Ver="3"><Coordinates PropType="vector&lt;double>" UCat="Length" Unt="m">0.002000000094994703,0.004699999932199247,    0</Coordinates></Centroid><MassMomentOfInertia ObjId="264" Type="MassMomentOfInertia" Ver="2"><Ixx PropType="double" UCat="MomentInertiaMass" Unt="kg m^2">1.247814034600073e-09</Ixx><Iyy PropType="double" UCat="MomentInertiaMass" Unt="kg m^2">2.259509622701612e-10</Iyy><Izz PropType="double" UCat="MomentInertiaMass" Unt="kg m^2">1.473764996870234e-09</Izz><CoordinateSystemRep ObjId="265" Type="CoordinateSystemRep" Ver="3"><Caption PropType="string">Undefined</Caption><CoordSystemIndex PropType="unsigned int">0</CoordSystemIndex><IsGlobal PropType="bool">false</IsGlobal><Param1 PropType="double">    1</Param1><Param2 PropType="double">    1</Param2><Singularity1 PropType="int">0</Singularity1><Singularity2 PropType="int">0</Singularity2><SolverCoordNumber PropType="unsigned int">0</SolverCoordNumber><Type PropType="string">Cartesian</Type><DSGePoint3d ObjId="267" Type="DSGePoint3d" Ver="3"><Coordinates PropType="vector&lt;double>" UCat="Length" Unt="m">0.002000000094994703,0.004699999932199247,    0</Coordinates></DSGePoint3d><Matrix3X3 ObjId="266" Type="Matrix3X3" Ver="2"><IsOrthogonal PropType="bool">false</IsOrthogonal><Row0 PropType="vector&lt;double>">    1,    0,    0</Row0><Row1 PropType="vector&lt;double>">    0,    1,    0</Row1><Row2 PropType="vector&lt;double>">    0,    0,    1</Row2></Matrix3X3></CoordinateSystemRep></MassMomentOfInertia></PartAttributes></AssemblyAttributes></GeometryAttributes><ServiceRep ObjId="236" Type="ServiceRep" Ver="2"><CoordinateSystemRep ObjId="36" Type="CoordinateSystemRep" Ver="3"><Caption PropType="string">Global Coordinate System</Caption><CoordSystemIndex PropType="unsigned int">0</CoordSystemIndex><IsGlobal PropType="bool">true</IsGlobal><Param1 PropType="double">    1</Param1><Param2 PropType="double">    1</Param2><Singularity1 PropType="int">0</Singularity1><Singularity2 PropType="int">0</Singularity2><SolverCoordNumber PropType="int">0</SolverCoordNumber><Type PropType="string">Cartesian</Type><DSGePoint3d ObjId="269" Type="DSGePoint3d" Ver="3"><Coordinates PropType="vector&lt;double>" UCat="Length" Unt="m">    0,    0,    0</Coordinates></DSGePoint3d><Matrix3X3 ObjId="268" Type="Matrix3X3" Ver="2"><IsOrthogonal PropType="bool">false</IsOrthogonal><Row0 PropType="vector&lt;double>">    1,    0,    0</Row0><Row1 PropType="vector&lt;double>">    0,    1,    0</Row1><Row2 PropType="vector&lt;double>">    0,    0,    1</Row2></Matrix3X3></CoordinateSystemRep></ServiceRep></EngineeringRep><GeometryRep ObjId="239" Type="GeometryRep" Ver="2"><ActiveAssembly PropType="unsigned int">1</ActiveAssembly><PartsAssembly PropType="string">000000000255ED08</PartsAssembly><Units PropType="string">m</Units></GeometryRep><MaterialLibraryRep ObjId="238" Type="MaterialLibraryRep" Ver="2"><FileName PropType="string">MatML.xml</FileName></MaterialLibraryRep><MeshRep ObjId="237" Type="MeshRep" Ver="2"><AssemblyMesh PropType="string">000000003B065C58</AssemblyMesh><Configuration PropType="unsigned int">229</Configuration><IndependentMesh PropType="string">IndependentMesh.bin</IndependentMesh><RigidBodyBehavior PropType="string">DimensionallyReduced</RigidBodyBehavior><Units PropType="string">m</Units></MeshRep><SolverRep ObjId="282" Type="SolverRep" Ver="2"><AnalysisType PropType="string">Modal</AnalysisType><IsCoupledFieldSystem PropType="bool">false</IsCoupledFieldSystem><PhysicsType PropType="string">Mechanical</PhysicsType><SolverTargetName PropType="string">ANSYS</SolverTargetName><SolverUnits PropType="int">11</SolverUnits><UnknownPointerId PropType="string">00000000084A71F0</UnknownPointerId><FEConnectorsRep ObjId="49" Type="FEConnectorsRep" Ver="2"><StepSelection PropType="int">0</StepSelection></FEConnectorsRep><FileManagementRep ObjId="284" Type="FileManagementRep" Ver="2"><DeleteUnneededFiles PropType="bool">true</DeleteUnneededFiles><SolverFileDirectory PropType="string"/><SolverFileRelativeDirectory PropType="string"/></FileManagementRep><ProcessControls ObjId="283" Type="ProcessControls" Ver="2"><DistributedSolve PropType="bool">true</DistributedSolve><IsLocal PropType="bool">true</IsLocal><IsRSMSolve PropType="bool">false</IsRSMSolve><ManualMemorySettings PropType="bool">false</ManualMemorySettings><MaxProcessors PropType="int">4</MaxProcessors></ProcessControls><AnalysisSettings CAEType="extObj"><ModalSettings version="1.0"><ModalControls version="1.0"><NumberOfModesToFind>6</NumberOfModesToFind><HasFollowonSpectrum>false</HasFollowonSpectrum><SpinSoftening>ProgramControlled</SpinSoftening></ModalControls><SolverControls version="1.0"><SolverType><ProgramControlled/></SolverType><WeakSprings><Off/></WeakSprings><DampedSolve>false</DampedSolve><StoreComplexSolution>true</StoreComplexSolution><ModeReuse><ProgramControlled/></ModeReuse><UseExistingModesymmFile><No/></UseExistingModesymmFile><ContactSplit><Off/></ContactSplit><CyclicMSUP>false</CyclicMSUP></SolverControls><OutputControls version="1.0"><Stress>false</Stress><Strain>false</Strain><Reactions>false</Reactions><GeneralMisc>false</GeneralMisc><SurfaceStress>false</SurfaceStress><BackStress>false</BackStress><ElementContactData>false</ElementContactData><ElementEulerAngles>false</ElementEulerAngles><ElementEnergies>false</ElementEnergies><ElementEnergies>false</ElementEnergies><ResultSetsType>Auto</ResultSetsType><CacheResultsInMemoryType>Never</CacheResultsInMemoryType><StoreModalResult>ProgramControlled</StoreModalResult><ExpandResultFrom>ProgramControlled</ExpandResultFrom><ProgControlledExpansion>Unknown</ProgControlledExpansion><NodalForcesType>No</NodalForcesType><CalculateParticipationFactorResult>ProgramControlled</CalculateParticipationFactorResult><CombineResultFiles>ProgramControlled</CombineResultFiles><ResultFileCompression>ProgramControlled</ResultFileCompression><TimePointsOptions>All</TimePointsOptions><ResultSets></ResultSets></OutputControls><SolverFileControls version="1.0"><SolverEngineType>ANSYS</SolverEngineType><SolverUnits>11</SolverUnits><SolverFilesDirectory>C:\Users\simon\Desktop\Test Ansys - Copia\test_files\dp0\SYS-6\MECH\</SolverFilesDirectory><SolverJobname>file</SolverJobname><ScratchSolverFilesDirectory>C:\Users\simon\Desktop\Test Ansys - Copia\_ProjectScratch\Scr7FA1\</ScratchSolverFilesDirectory><AdditionalList></AdditionalList><SaveANSYSDB>false</SaveANSYSDB><ContactSummary>kAnalysisSettingsContactSummaryProgramControlled</ContactSummary><DeleteUnusedFiles>true</DeleteUnusedFiles><ResultFile>file.rst</ResultFile></SolverFileControls><CyclicControls version="1.0"><Activation><Activation>0</Activation></Activation></CyclicControls><DampingControls version="1.0"><BetaDamping>0.</BetaDamping><AlphaDamping>0.</AlphaDamping><ConstantStructuralDampingCoefficient>0.</ConstantStructuralDampingCoefficient></DampingControls><RotordynamicsControls version="1.0"><CoriolisEffect>No</CoriolisEffect><ReferenceFrameStationary>Stationary</ReferenceFrameStationary><RotatingDampingEffect>No</RotatingDampingEffect><CampbellDiagram>No</CampbellDiagram><Sorting>Yes</Sorting><ModalNumberofPoints>2</ModalNumberofPoints><ModeReuse>ProgramControlled</ModeReuse></RotordynamicsControls></ModalSettings></AnalysisSettings></SolverRep></CAERep>